[
  {
    "candidateId": 1,
    "name": "Евгений Рябов",
    "city": "Гатчино",
    "age": 45,
    "description": "Евгений Рябов, 45 лет, проживает в Гатчине, Ленинградская область, Россия. ...",
    "photo": "/src/constant/Photo_Candidates/ryabov.png",
    "voteID": 1
  },
  {
    "candidateId": 2,
    "name": "Седьмо Илья",
    "city": "Ухта",
    "age": 37,
    "description": "Илья Седьмо - специалист в области IT с 15-летним опытом.",
    "photo": "/src/constant/Photo_Candidates/sedmo.png",
    "voteID": 2
  }
]
